autotestreg/__init__.py
autotestreg/autotest.py
autotestreg-0.3.1.dist-info/METADATA
autotestreg-0.3.1.dist-info/WHEEL
autotestreg-0.3.1.dist-info/entry_points.txt
autotestreg-0.3.1.dist-info/top_level.txt
autotestreg-0.3.1.dist-info/RECORD
