Metadata-Version: 2.4
Name: autotestreg
Version: 0.3.1
Summary: Automatically test your functions to see if you have changed their behavior by mistake!
Author-email: Nicolas Micaux <micaux.nicolas@gmail.com>
Project-URL: Homepage, https://github.com/NicolasMICAUX/autotestreg
Keywords: test,regression,automatically
Classifier: Development Status :: 3 - Alpha
Classifier: Intended Audience :: Developers
Classifier: Natural Language :: English
Classifier: Topic :: Software Development
Classifier: Topic :: Software Development :: Debuggers
Classifier: Topic :: Utilities
Classifier: Programming Language :: Python :: 3
Classifier: Programming Language :: Python :: 3.5
Classifier: Programming Language :: Python :: 3.6
Classifier: Programming Language :: Python :: 3.7
Classifier: Programming Language :: Python :: 3.8
Classifier: Programming Language :: Python :: 3.9
Classifier: Programming Language :: Python :: 3.10
Classifier: Programming Language :: Python :: 3.11
Requires-Python: >=3.5
Requires-Dist: dill
